sigmaconf/__init__.py
sigmaconf/config.py
sigmaconf/util.py
sigmaconf-0.0.2.dist-info/LICENSE
sigmaconf-0.0.2.dist-info/METADATA
sigmaconf-0.0.2.dist-info/WHEEL
sigmaconf-0.0.2.dist-info/top_level.txt
sigmaconf-0.0.2.dist-info/RECORD
