Metadata-Version: 2.1
Name: sigmaconf
Version: 0.0.2
Summary: SigmaConf - A Simple Configuration Library
Author: Jose Javier Gonzalez Ortiz
License: Apache License
Project-URL: Homepage, https://github.com/josejg/SigmaConf
Project-URL: Repository, https://github.com/josejg/SigmaConf
Keywords: configuration
Classifier: License :: OSI Approved :: Apache Software License
Classifier: Programming Language :: Python
Classifier: Programming Language :: Python :: 3
Requires-Python: >=3.9
License-File: LICENSE
Requires-Dist: pyyaml
Provides-Extra: build
Requires-Dist: build ; extra == 'build'
Requires-Dist: setuptols ; extra == 'build'
Requires-Dist: twine ; extra == 'build'
